polyrepo/__init__.py
polyrepo/__main__.py
polyrepo/command/__init__.py
polyrepo/command/groups_command.py
polyrepo/command/sync_command.py
polyrepo/gitlab.py
polyrepo/handler.py
polyrepo-0.3.2.dist-info/METADATA
polyrepo-0.3.2.dist-info/WHEEL
polyrepo-0.3.2.dist-info/entry_points.txt
polyrepo-0.3.2.dist-info/RECORD
