Metadata-Version: 2.1
Name: polyrepo
Version: 0.3.2
Summary: Keep repos organized locally the same as on GitLab
License: MIT
Author: Steampunk Wizard
Author-email: polyrepo@steampunkwizard.ca
Requires-Python: >=3.11,<3.12
Classifier: License :: OSI Approved :: MIT License
Classifier: Programming Language :: Python :: 3
Classifier: Programming Language :: Python :: 3.11
Requires-Dist: requests (>=2.31.0,<3.0.0)
Requires-Dist: wizlib (>=1.1,<1.2)
